objectit_airflow_monitoring/Slack.py
objectit_airflow_monitoring/__init__.py
objectit_airflow_monitoring/test_slack.py
objectit_airflow_monitoring_test-0.0.2.dist-info/DESCRIPTION.rst
objectit_airflow_monitoring_test-0.0.2.dist-info/METADATA
objectit_airflow_monitoring_test-0.0.2.dist-info/RECORD
objectit_airflow_monitoring_test-0.0.2.dist-info/WHEEL
objectit_airflow_monitoring_test-0.0.2.dist-info/metadata.json
objectit_airflow_monitoring_test-0.0.2.dist-info/top_level.txt
