Metadata-Version: 2.0
Name: objectit-airflow-monitoring-test
Version: 0.0.2
Summary: Integrates Slack, Email, Rollbar and others to Airflow and sends notifications
Home-page: UNKNOWN
Author: Linton
Author-email: linton@example.org
License: UNKNOWN
Platform: UNKNOWN
Classifier: Programming Language :: Python :: 3
Classifier: License :: OSI Approved :: MIT License
Classifier: Operating System :: OS Independent
Requires-Python: >=3.6
